pywmbus/__init__.py
pywmbus/__version__.py
pywmbus/const.py
pywmbus/cul_stick.py
pywmbus/datagram.py
pywmbus/datagram_field.py
pywmbus/datagram_headless.py
pywmbus/datagram_long.py
pywmbus/datagram_record.py
pywmbus/datagram_short.py
pywmbus/exceptions.py
pywmbus/helpers.py
pywmbus/serial_device.py
pywmbus-0.0.7.data/scripts/parser.py
pywmbus-0.0.7.dist-info/DESCRIPTION.rst
pywmbus-0.0.7.dist-info/METADATA
pywmbus-0.0.7.dist-info/RECORD
pywmbus-0.0.7.dist-info/WHEEL
pywmbus-0.0.7.dist-info/metadata.json
pywmbus-0.0.7.dist-info/top_level.txt
