Metadata-Version: 2.0
Name: pywmbus
Version: 0.0.7
Summary: wM-Bus implementation in Python
Home-page: https://github.com/jalmeroth/pywmbus
Author: Jan Almeroth
Author-email: jan+pywmbus@almeroth.com
License: MIT
Platform: any
Classifier: License :: OSI Approved :: MIT License
Classifier: Programming Language :: Python :: 3
Classifier: Programming Language :: Python :: 3.6
Requires-Dist: crcmod
Requires-Dist: pyserial
